{
    "childrenSlugs": [],
    "markdownContent": " # Клан игровых мастеров\nДанный клан относится к представителям администрации игры.  \nОни следят за порядком, помогают решать возникающие игровые вопросы и проводят различные [мероприятия](/sys/event).\n\n**Иконка клана:** ![w=20 h=20](clan/25.png)\n### 📋 Состав\n**Активные:**\n- beta_01  \n- Help  \n- ProstoV  \n- Plen\n_Сейчас не активны:_\n- Poor_man  \n- Just  \n- Jertva  \n- Alexbot  \n- Kot  \n- XP  \n- Solar  \n___\n### 📢 Связь с ГМами\n\nЧтобы отправить сообщение сразу всем ГМам, используйте команду:  \n[/help](/cmd ui insert_text_input /help) ваш вопрос\n\n💡 *Формулируйте вопрос максимально чётко — это ускорит получение ответа.*\n",
    "parentSlug": "sys/clan",
    "parentTitles": [
        "ЕСИ",
        "Кланы"
    ],
    "slug": "sys/clan/25",
    "tagSlugs": [],
    "title": "Game_Master"
}