{
    "childrenSlugs": [],
    "markdownContent": "# Псевдоним персонажа\nПсевдоним персонажа — такой же важный идентификатор, как и никнейм, но более локальный: он распространяется не на весь аккаунт, а только на конкретного персонажа.\n\nИзначально персонаж появляется без какого-либо псевдонима. Игрок выбирает его самостоятельно, чтобы было проще идентифицировать персонажа в списке. Так же, как и никнейм, псевдоним можно спокойно изменить в любой момент — в параметрах персонажа.\n\nДругие игроки видят его, когда наводятся на робота.\n",
    "parentSlug": "sys/character",
    "parentTitles": [
        "ЕСИ",
        "Персонаж"
    ],
    "slug": "sys/character/psevdo",
    "tagSlugs": [],
    "title": "Псевдоним персонажа"
}