{
    "childrenSlugs": [],
    "markdownContent": "# Зачистка боссов\nДанное задание доступно после получения 9-го уровня у персонажа, в дальнейшем для следующих этапов потребуется больше уровней.\n\nПолучить его можно в Правительстве.\nЗа выполненные задания можно получить:\n\nБоны\nОчки умений\nОборудование\n\n# #1\n**Требуемый уровень: 9**\n**Награда:**\n- *5.000* бон\n- Накопитель 12 лвл\n**Цели:**\n- Тук босс: *1*\n\n# #2\n**Требуемый уровень: 11**\n**Награда:**\n- *8.000* бон\n- Трюм 12 лвл\n**Цели:**\n- Тук босс: *2*\n\n# #3\n**Требуемый уровень: 13**\n**Награда:**\n- *9.000* бон\n- Реактор 16 лвл\n**Цели:**\n- Тук босс: *3*\n\n# #4\n**Требуемый уровень: 15**\n**Награда:**\n- *12.000* бон\n- Накопитель 16 лвл\n**Цели:**\n- Паук босс: *1*\n\n# #5\n**Требуемый уровень: 17**\n**Награда:**\n- *15.000* бон\n- Броня 18 лвл\n- *5* очков умений\n**Цели:**\n- Паук босс: *1*\n- Тук босс: *1*\n\n# #6\n**Требуемый уровень: 19**\n**Награда:**\n- *20.000* бон\n**Цели:**\n- Паук босс: *2*\n- Тук босс: *2*\n\n# #7\n**Требуемый уровень: 21**\n**Награда:**\n- *30.000* бон\n**Цели:**\n- Паук босс: *3*\n- Тук босс: *3*\n\n# #8\n**Требуемый уровень: 23**\n**Награда:**\n- *40.000* бон\n- Чип ТРЮМ v.3\n**Цели:**\n- Скорпион босс: *1*\n\n# #9\n**Требуемый уровень: 25**\n**Награда:**\n- *50.000* бон\n**Цели:**\n- Скорпион босс: *2*\n\n# #10\n**Требуемый уровень: 27**\n**Награда:**\n- *70.000* бон\n- *5* очков умений\n**Цели:**\n- Скорпион босс: *3*\n- Паук босс: *3*\n- Тук босс: *3*\n\n# #11\n**Требуемый уровень: 29**\n**Награда:**\n- *80.000* бон\n**Цели:**\n- Скорпион босс: *4*\n- Паук босс: *6*\n- Тук босс: *8*\n\n# #12\n**Требуемый уровень: 31**\n**Награда:**\n- *120.000* бон\n**Цели:**\n- Богомол босс: *1*\n\n# #13\n**Требуемый уровень: 33**\n**Награда:**\n- *160.000* бон\n- Чип ЭНЕРГОСНАБЖЕНИЕ v.4\n**Цели:**\n- Богомол босс: *2*\n\n# #14\n**Требуемый уровень: 35**\n**Награда:**\n- *200.000* бон\n**Цели:**\n- Богомол босс: *3*\n\n# #15\n**Требуемый уровень: 37**\n**Награда:**\n- *240.000* бон\n- Рк защита малая\n- *5* очков умений\n**Цели:**\n- Паук босс: *8*\n- Богомол босс: *3*\n- Скорпион босс: *6*\n\n# #16\n**Требуемый уровень: 39**\n**Награда:**\n- *250.000* бон\n**Цели:**\n- Богомол босс: *4*\n- Скорпион босс: *10*\n\n# #17\n**Требуемый уровень: 41**\n**Награда:**\n- *300.000* бон\n**Цели:**\n- Червь босс: *1*\n\n# #18\n**Требуемый уровень: 43**\n**Награда:**\n- *350.000* бон\n**Цели:**\n- Червь босс: *2*\n\n# #19\n**Требуемый уровень: 45**\n**Награда:**\n- *400.000* бон\n**Цели:**\n- Червь босс: *3*\n- Богомол босс: *6*\n- Скорпион босс: *12*\n\n# #20\n**Требуемый уровень: 47**\n**Награда:**\n- *500.000* бон\n- *5* очков умений\n**Цели:**\n- Червь босс: *4*\n- Богомол босс: *8*\n- Скорпион босс: *14*\n\n# #21\n**Требуемый уровень: 49**\n**Награда:**\n- *600.000* бон\n**Цели:**\n- Медвед босс: *1*\n\n# #22\n**Требуемый уровень: 51**\n**Награда:**\n- *650.000* бон\n**Цели:**\n- Медвед босс: *2*\n\n# #23\n**Требуемый уровень: 53**\n**Награда:**\n- *700.000* бон\n**Цели:**\n- Медвед босс: *2*\n- Червь босс: *4*\n- Богомол босс: *8*\n\n# #24\n**Требуемый уровень: 55**\n**Награда:**\n- *750.000* бон\n**Цели:**\n- Медвед босс: *4*\n- Червь босс: *8*\n\n# #25\n**Требуемый уровень: 57**\n**Награда:**\n- *800.000* бон\n- *5* очков умений\n**Цели:**\n- Варан босс: *1*\n\n# #26\n**Требуемый уровень: 59**\n**Награда:**\n- *850.000* бон\n**Цели:**\n- Варан босс: *2*\n\n# #27\n**Требуемый уровень: 61**\n**Награда:**\n- *900.000* бон\n**Цели:**\n- Варан босс: *3*\n\n# #28\n**Требуемый уровень: 63**\n**Награда:**\n- *920.000* бон\n**Цели:**\n- Варан босс: *3*\n- Медвед босс: *4*\n- Червь босс: *8*\n\n# #29\n**Требуемый уровень: 65**\n**Награда:**\n- *950.000* бон\n**Цели:**\n- Варан босс: *4*\n- Медвед босс: *6*\n\n# #30\n**Требуемый уровень: 67**\n**Награда:**\n- *1.000.000* бон\n- *5* очков умений\n**Цели:**\n- Варан босс: *6*\n- Медвед босс: *10*\n- Червь босс: *12*\n\n# #31\n**Требуемый уровень: 69**\n**Награда:**\n- *1.200.000* бон\n**Цели:**\n- Слепень босс: *1*\n\n# #32\n**Требуемый уровень: 71**\n**Награда:**\n- *1.250.000* бон\n**Цели:**\n- Слепень босс: *1*\n- Варан босс: *1*\n\n# #33\n**Требуемый уровень: 73**\n**Награда:**\n- *1.300.000* бон\n**Цели:**\n- Слепень босс: *2*\n- Варан босс: *4*\n\n# #34\n**Требуемый уровень: 75**\n**Награда:**\n- *1.350.000* бон\n**Цели:**\n- Слепень босс: *3*\n- Варан босс: *8*\n- Медвед босс: *16*\n\n# #35\n**Требуемый уровень: 77**\n**Награда:**\n- *1.400.000* бон\n- *5* очков умений\n**Цели:**\n- Слизень босс: *1*\n\n# #36\n**Требуемый уровень: 79**\n**Награда:**\n- *1.450.000* бон\n**Цели:**\n- Слизень босс: *2*\n\n# #37\n**Требуемый уровень: 81**\n**Награда:**\n- *1.500.000* бон\n**Цели:**\n- Слизень босс: *2*\n- Слепень босс: *4*\n\n# #38\n**Требуемый уровень: 83**\n**Награда:**\n- *1.600.000* бон\n**Цели:**\n- Слизень босс: *3*\n- Слепень босс: *6*\n- Варан босс: *10*\n\n# #39\n**Требуемый уровень: 85**\n**Награда:**\n- *1.700.000* бон\n**Цели:**\n- Слизень босс: *4*\n- Слепень босс: *10*\n- Варан босс: *14*\n\n# #40\n**Требуемый уровень: 87**\n**Награда:**\n- *1.800.000* бон\n- *5* очков умений\n**Цели:**\n- Каракурт: *1*\n\n# #41\n**Требуемый уровень: 89**\n**Награда:**\n- *1.900.000* бон\n**Цели:**\n- Корикс: *1*\n\n# #42\n**Требуемый уровень: 91**\n**Награда:**\n- *2.000.000* бон\n**Цели:**\n- Эцитон: *1*\n\n# #43\n**Требуемый уровень: 93**\n**Награда:**\n- *2.100.000* бон\n**Цели:**\n- Эцитон: *2*\n- Слизень босс: *6*\n\n# #44\n**Требуемый уровень: 95**\n**Награда:**\n- *2.200.000* бон\n**Цели:**\n- Эцитон: *2*\n- Каракурт: *2*\n- Слизень босс: *8*\n\n# #45\n**Требуемый уровень: 97**\n**Награда:**\n- *2.500.000* бон\n**Цели:**\n- Эцитон: *3*\n- Каракурт: *3*\n- Корикс: *3*\n- Слизень босс: *16*\n\n# #46\n**Требуемый уровень: 99**\n**Награда:**\n- *3.000.000* бon\n- *10* очков умений\n**Цели:**\n- Эцитон: *10*\n- Каракурт: *10*\n- Корикс: *10*",
    "parentSlug": "sys/tasks",
    "parentTitles": [
        "ЕСИ",
        "Задания"
    ],
    "slug": "sys/tasks/destroy-bosses",
    "tagSlugs": [
        "quest",
        "wiki"
    ],
    "title": "Зачистка боссов"
}